<?xml version="1.0" encoding="UTF-8"?>

<ProcessOsmDatabase inputFileName="spain" outputFileName="bus_spain">

  <relation type="route_master">
  
    <filter route_master="bus">
      <check route="BusNetwork">
      </check>
    </filter>

  </relation>

  <relation type="route">

    <filter route="bus">
      <check route="BusNetwork">
      </check>
    </filter>

  </relation>

  <relation type="network">

    <filter name="Red de Autobuses de Largo Recorrido">
      <check count="1" route="PTv2">
      </check>
    </filter>

    <filter name="Red de buses regulares EMT (Madrid)">
      <check count="1" route="PTv2">
      </check>
    </filter>

    <filter name="Red de buses nocturnos EMT (Madrid)">
      <check count="1" route="PTv2">
      </check>
    </filter>

    <filter name="Red de buses universitarios EMT (Madrid)">
      <check count="1" route="PTv2">
      </check>
    </filter>

    <filter network="ES:GU">
      <check count="1" route="PTv2">
      </check>
    </filter>

    <filter network="ES:GU:Azuqueca de Henares">
      <check count="1" route="PTv2">
      </check>
    </filter>

    <filter network="ES:GU:Guadalajara">
      <check count="1" route="PTv2">
      </check>
    </filter>

    <filter network="ES:M">
      <check count="1" route="PTv2">
      </check>
    </filter>

    <filter network="ES:M:Alcalá de Henares">
      <check count="1" route="PTv2">
      </check>
    </filter>

    <filter network="ES:M:Alcorcón">
      <check count="1" route="PTv2">
      </check>
    </filter>

    <filter network="ES:M:Aranjuez">
      <check count="1" route="PTv2">
      </check>
    </filter>

    <filter network="ES:M:Arganda del Rey">
      <check count="1" route="PTv2">
      </check>
    </filter>

    <filter network="ES:M:Cercedilla">
      <check count="1" route="PTv2">
      </check>
    </filter>

    <filter network="ES:M:Ciempozuelos">
      <check count="1" route="PTv2">
      </check>
    </filter>

    <filter network="ES:M:Collado Villalba">
      <check count="1" route="PTv2">
      </check>
    </filter>

    <filter network="ES:M:Colmenar Viejo">
      <check count="1" route="PTv2">
      </check>
    </filter>

    <filter network="ES:M:Coslada-San Fernando de Henares">
      <check count="1" route="PTv2">
      </check>
    </filter>

    <filter network="ES:M:Fuenlabrada">
      <check count="1" route="PTv2">
      </check>
    </filter>

    <filter network="ES:M:Getafe">
      <check count="1" route="PTv2">
      </check>
    </filter>

    <filter network="ES:M:Guadarrama">
      <check count="1" route="PTv2">
      </check>
    </filter>

    <filter network="ES:M:Leganés">
      <check count="1" route="PTv2">
      </check>
    </filter>

    <filter network="ES:M:Morata de Tajuña">
      <check count="1" route="PTv2">
      </check>
    </filter>

    <filter network="ES:M:Móstoles">
      <check count="1" route="PTv2">
      </check>
    </filter>

    <filter network="ES:M:Navalcarnero">
      <check count="1" route="PTv2">
      </check>
    </filter>

    <filter network="ES:M:Parla">
      <check count="1" route="PTv2">
      </check>
    </filter>

    <filter network="ES:M:Pinto">
      <check count="1" route="PTv2">
      </check>
    </filter>

    <filter network="ES:M:Rivas Vaciamadrid">
      <check count="1" route="PTv2">
      </check>
    </filter>

    <filter network="ES:M:San Martín de la Vega">
      <check count="1" route="PTv2">
      </check>
    </filter>

    <filter network="ES:M:Torrejón de Ardoz">
      <check count="1" route="PTv2">
      </check>
      <convert>
      </convert>
    </filter>

    <filter network="ES:M:Valdemoro">
      <check count="1" route="PTv2">
      </check>
    </filter>

    <filter network="ES:M:Villanueva de la Cañada">
      <check count="1" route="PTv2">
      </check>
    </filter>

    <filter network="ES:SG">
      <check count="1" route="PTv2">
      </check>
    </filter>

    <filter network="ES:SG:Segovia">
      <check count="1" route="PTv2">
      </check>
    </filter>

    <filter network="ES:TO:Escalona de Alberche">
      <check count="1" route="PTv2">
      </check>
    </filter>

  </relation>

</ProcessOsmDatabase>

